bsky/__init__.py
bsky-0.0.0.dist-info/LICENSE
bsky-0.0.0.dist-info/METADATA
bsky-0.0.0.dist-info/WHEEL
bsky-0.0.0.dist-info/top_level.txt
bsky-0.0.0.dist-info/RECORD
