Metadata-Version: 2.1
Name: bsky
Version: 0.0.0
Summary: Simple, idiomatic client library for atproto.com (Bluesky)
Author-email: bryan newbold <bnewbold@robocracy.org>
Project-URL: Homepage, https://gitlab.com/bnewbold/bsky-py
Project-URL: Bug Tracker, https://gitlab.com/bnewbold/bsky-py/-/issues
Classifier: Programming Language :: Python :: 3
Classifier: License :: OSI Approved :: MIT License
Classifier: Operating System :: OS Independent
Requires-Python: >=3.8
License-File: LICENSE
